usgs_mbe/__init__.py
usgs_mbe/main.py
usgs_mbe-0.1.4.dist-info/entry_points.txt
usgs_mbe-0.1.4.dist-info/WHEEL
usgs_mbe-0.1.4.dist-info/METADATA
usgs_mbe-0.1.4.dist-info/RECORD
