Metadata-Version: 2.1
Name: usgs-mbe
Version: 0.1.4
Summary: USGS MovingBedExtraction - Parser to generate summary data from ADCP files for the USGS.
Home-page: https://github.com/NickBenthem/ADCP-Moving-Bed-Extraction
License: MIT
Keywords: ADCP,MovingBedExtraction,USGS
Author: Nick Benthem
Author-email: nick@benthem.io
Requires-Python: >=3.8,<4.0
Classifier: License :: OSI Approved :: MIT License
Classifier: Programming Language :: Python :: 3
Classifier: Programming Language :: Python :: 3.8
Classifier: Programming Language :: Python :: 3.9
Requires-Dist: importlib-metadata (>=4.0.1,<5.0.0)
Requires-Dist: lxml (>=4.6.3,<5.0.0)
Requires-Dist: pandas (>=1.2.4,<2.0.0)
Requires-Dist: requests (>=2.25.1,<3.0.0)
Requires-Dist: xmltodict (>=0.12.0,<0.13.0)
Project-URL: Repository, https://github.com/NickBenthem/ADCP-Moving-Bed-Extraction
